setup.py
esfdw/__init__.py
esfdw/es_helper.py
esfdw/esfdw.py
esfdw/mapping_to_schema.py
esfdw.egg-info/PKG-INFO
esfdw.egg-info/SOURCES.txt
esfdw.egg-info/dependency_links.txt
esfdw.egg-info/top_level.txt