Metadata-Version: 1.1
Name: esfdw
Version: 0.1.1
Summary: PostgreSQL foreign data wrapper for Elasticsearch
Home-page: https://github.com/rtkwlf/esfdw
Author: Arctic Wolf Networks, Inc.
Author-email: info@arcticwolf.com
License: MIT
Download-URL: https://github.com/rtkwlf/esfdw/tarball/0.1.1
Platform: UNKNOWN
